{
  "isStruct": false,
  "key": [
    "INN"
  ],
  "semantic": "fullName",
  "name": "organization",
  "version": "20160916",
  "caption": "Организация",
  "ancestor": null,
  "container": null,
  "creationTracker": "",
  "changeTracker": "",
  "history": 0,
  "journaling": false,
  "compositeIndexes": null,
  "properties": [
    {
      "orderNumber": 10,
      "name": "INN",
      "caption": "ИНН",
      "type": 0,
      "size": 12,
      "decimals": 0,
      "allowedFileTypes": null,
      "maxFileCount": 0,
      "nullable": false,
      "readonly": false,
      "indexed": false,
      "unique": true,
      "autoassigned": false,
      "hint": null,
      "defaultValue": null,
      "refClass": "",
      "itemsClass": "",
      "backRef": "",
      "backColl": "",
      "binding": "",
      "semantic": null,
      "selConditions": [],
      "selSorting": [],
      "selectionProvider": null,
      "indexSearch": false,
      "eagerLoading": false,
      "formula": null
    },
    {
      "orderNumber": 20,
      "name": "name",
      "caption": "Краткое наименование",
      "type": 0,
      "size": 64,
      "decimals": 0,
      "allowedFileTypes": null,
      "maxFileCount": 0,
      "nullable": true,
      "readonly": false,
      "indexed": false,
      "unique": false,
      "autoassigned": false,
      "hint": null,
      "defaultValue": null,
      "refClass": "",
      "itemsClass": "",
      "backRef": "",
      "backColl": "",
      "binding": "",
      "semantic": null,
      "selConditions": [],
      "selSorting": [],
      "selectionProvider": null,
      "indexSearch": false,
      "eagerLoading": false,
      "formula": null
    },
    {
      "orderNumber": 55,
      "name": "headOrg",
      "caption": "Вышестоящая организация",
      "type": 13,
      "size": null,
      "decimals": 0,
      "allowedFileTypes": null,
      "maxFileCount": 0,
      "nullable": true,
      "readonly": false,
      "indexed": false,
      "unique": false,
      "autoassigned": false,
      "hint": null,
      "defaultValue": null,
      "refClass": "organization",
      "itemsClass": "",
      "backRef": "",
      "backColl": "",
      "binding": "",
      "semantic": null,
      "selConditions": [],
      "selSorting": [],
      "selectionProvider": null,
      "indexSearch": false,
      "eagerLoading": false,
      "formula": null
    },
    {
      "orderNumber": 56,
      "name": "head",
      "caption": "Руководитель",
      "type": 13,
      "size": null,
      "decimals": 0,
      "allowedFileTypes": null,
      "maxFileCount": 0,
      "nullable": true,
      "readonly": false,
      "indexed": false,
      "unique": false,
      "autoassigned": false,
      "hint": null,
      "defaultValue": null,
      "refClass": "employee",
      "itemsClass": "",
      "backRef": "",
      "backColl": "",
      "binding": "",
      "semantic": null,
      "selConditions": [],
      "selSorting": [],
      "selectionProvider": null,
      "indexSearch": false,
      "eagerLoading": false,
      "formula": null
    },
    {
      "orderNumber": 57,
      "name": "employee",
      "caption": "Должностные лица",
      "type": 14,
      "size": null,
      "decimals": 0,
      "allowedFileTypes": null,
      "maxFileCount": 0,
      "nullable": true,
      "readonly": false,
      "indexed": false,
      "unique": false,
      "autoassigned": false,
      "hint": null,
      "defaultValue": null,
      "refClass": "",
      "itemsClass": "employee",
      "backRef": "organization",
      "backColl": "",
      "binding": "",
      "semantic": null,
      "selConditions": [],
      "selSorting": [],
      "selectionProvider": null,
      "indexSearch": false,
      "eagerLoading": false,
      "formula": null
    },
    {
      "orderNumber": 30,
      "name": "fullName",
      "caption": "Полное наименование",
      "type": 0,
      "size": 256,
      "decimals": 0,
      "allowedFileTypes": null,
      "maxFileCount": 0,
      "nullable": false,
      "readonly": false,
      "indexed": false,
      "unique": false,
      "autoassigned": false,
      "hint": null,
      "defaultValue": null,
      "refClass": "",
      "itemsClass": "",
      "backRef": "",
      "backColl": "",
      "binding": "",
      "semantic": null,
      "selConditions": [],
      "selSorting": [],
      "selectionProvider": null,
      "indexSearch": false,
      "eagerLoading": false,
      "formula": null
    },
    {
      "orderNumber": 40,
      "name": "adress",
      "caption": "Адрес юридический",
      "type": 13,
      "size": null,
      "decimals": 0,
      "allowedFileTypes": null,
      "maxFileCount": 0,
      "nullable": true,
      "readonly": false,
      "indexed": false,
      "unique": false,
      "autoassigned": false,
      "hint": null,
      "defaultValue": null,
      "refClass": "adress",
      "itemsClass": "",
      "backRef": "",
      "backColl": "",
      "binding": "",
      "semantic": null,
      "selConditions": [],
      "selSorting": [],
      "selectionProvider": null,
      "indexSearch": false,
      "eagerLoading": false,
      "formula": null
    },
    {
      "orderNumber": 50,
      "name": "postAdress",
      "caption": "Адрес фактический (почтовый)",
      "type": 13,
      "size": null,
      "decimals": 0,
      "allowedFileTypes": null,
      "maxFileCount": 0,
      "nullable": true,
      "readonly": false,
      "indexed": false,
      "unique": false,
      "autoassigned": false,
      "hint": null,
      "defaultValue": null,
      "refClass": "adress",
      "itemsClass": "",
      "backRef": "",
      "backColl": "",
      "binding": "",
      "semantic": null,
      "selConditions": [],
      "selSorting": [],
      "selectionProvider": null,
      "indexSearch": false,
      "eagerLoading": false,
      "formula": null
    },
    {
      "orderNumber": 60,
      "name": "phone",
      "caption": "Телефон",
      "type": 0,
      "size": 12,
      "decimals": 0,
      "allowedFileTypes": null,
      "maxFileCount": 0,
      "nullable": true,
      "readonly": false,
      "indexed": false,
      "unique": false,
      "autoassigned": false,
      "hint": null,
      "defaultValue": null,
      "refClass": "",
      "itemsClass": "",
      "backRef": "",
      "backColl": "",
      "binding": "",
      "semantic": null,
      "selConditions": [],
      "selSorting": [],
      "selectionProvider": null,
      "indexSearch": false,
      "eagerLoading": false,
      "formula": null
    },
    {
      "orderNumber": 70,
      "name": "person",
      "caption": "Персонал",
      "type": 14,
      "size": null,
      "decimals": 0,
      "allowedFileTypes": null,
      "maxFileCount": 0,
      "nullable": true,
      "readonly": false,
      "indexed": false,
      "unique": false,
      "autoassigned": false,
      "hint": null,
      "defaultValue": null,
      "refClass": null,
      "itemsClass": "person",
      "backRef": "organization",
      "backColl": "",
      "binding": "",
      "semantic": null,
      "selConditions": [],
      "selSorting": [],
      "selectionProvider": null,
      "indexSearch": false,
      "eagerLoading": false,
      "formula": null
    },
    {
      "orderNumber": 80,
      "name": "type",
      "caption": "Тип организации",
      "type": 0,
      "size": null,
      "decimals": 0,
      "allowedFileTypes": null,
      "maxFileCount": 0,
      "nullable": true,
      "readonly": false,
      "indexed": false,
      "unique": false,
      "autoassigned": false,
      "hint": null,
      "defaultValue": null,
      "refClass": "",
      "itemsClass": "",
      "backRef": "",
      "backColl": "",
      "binding": "",
      "semantic": null,
      "selConditions": [],
      "selSorting": [],
      "selectionProvider": {
        "type": "SIMPLE",
        "list": [
          {
            "key": "customer",
            "value": "Заказчик"
          },
          {
            "key": "executor",
            "value": "Исполнитель"
          },
          {
            "key": "operator",
            "value": "Оператор"
          }
        ],
        "matrix": [],
        "parameters": [],
        "hq": ""
      },
      "indexSearch": false,
      "eagerLoading": false,
      "formula": null
    },
    {
      "orderNumber": 100,
      "name": "geocoor",
      "caption": "Геокоординаты",
      "type": 100,
      "size": null,
      "decimals": 0,
      "allowedFileTypes": null,
      "maxFileCount": 0,
      "nullable": true,
      "readonly": false,
      "indexed": false,
      "unique": false,
      "autoassigned": false,
      "hint": null,
      "defaultValue": null,
      "refClass": "",
      "itemsClass": "",
      "backRef": "",
      "backColl": "",
      "binding": "",
      "semantic": null,
      "selConditions": [],
      "selSorting": [],
      "selectionProvider": null,
      "indexSearch": false,
      "eagerLoading": false,
      "formula": null
    },
    {
      "orderNumber": 1010,
      "name": "verify",
      "caption": "Проверен",
      "type": 10,
      "size": null,
      "decimals": 0,
      "allowedFileTypes": null,
      "maxFileCount": 0,
      "nullable": false,
      "readonly": false,
      "indexed": false,
      "unique": false,
      "autoassigned": false,
      "hint": null,
      "defaultValue": "false",
      "refClass": "",
      "itemsClass": "",
      "backRef": "",
      "backColl": "",
      "binding": "",
      "semantic": null,
      "selConditions": [],
      "selSorting": [],
      "selectionProvider": null,
      "indexSearch": false,
      "eagerLoading": false,
      "formula": null
    }
  ],
  "metaVersion": "2.0.0"
}